readthedocs_custom_steps.py
readthedocs_custom_steps-0.2.1.dist-info/METADATA
readthedocs_custom_steps-0.2.1.dist-info/WHEEL
readthedocs_custom_steps-0.2.1.dist-info/top_level.txt
readthedocs_custom_steps-0.2.1.dist-info/RECORD
