Metadata-Version: 2.1
Name: readthedocs-custom-steps
Version: 0.2.1
Summary: A hack to run custom steps when building documentation on Read the Docs.
Home-page: UNKNOWN
Author: Niklas Rosenstein
Author-email: rosensteinniklas@gmail.com
License: UNKNOWN
Platform: UNKNOWN
Requires-Dist: PyYAML (<6.0.0,>=5.0)
